gnuplot_gen/__init__.py
gnuplot_gen/cli.py
gnuplot_gen/gnuplot_template.py
gnuplot_gen/utils.py
gplotter-0.1.2.dist-info/METADATA
gplotter-0.1.2.dist-info/WHEEL
gplotter-0.1.2.dist-info/entry_points.txt
gplotter-0.1.2.dist-info/top_level.txt
gplotter-0.1.2.dist-info/RECORD
