Metadata-Version: 2.4
Name: gplotter
Version: 0.1.2
Summary: CLI-based GNUPlot script generator
Home-page: https://github.com/KishantLab/gplotter.git
Author: Kishan Tamboli
Author-email: kishant@iitbhilai.ac.in
Classifier: Programming Language :: Python :: 3
Classifier: License :: OSI Approved :: MIT License
Requires-Python: >=3.7
Dynamic: author
Dynamic: author-email
Dynamic: classifier
Dynamic: description
Dynamic: description-content-type
Dynamic: home-page
Dynamic: requires-python
Dynamic: summary
